README.md
setup.py
core/__init__.py
core/useful.py
core/util.py
goodies.egg-info/PKG-INFO
goodies.egg-info/SOURCES.txt
goodies.egg-info/dependency_links.txt
goodies.egg-info/top_level.txt
transforms/__init__.py
transport/__init__.py