Metadata-Version: 1.0
Name: goodies
Version: 0.1.0
Summary: Aarons core tools
Home-page: https://github.com/free-soellingeraj/goodies
Author: AJS Consult LLC
Author-email: ajs.consult.llc@gmail.com
License: UNKNOWN
Platform: UNKNOWN
